SMS_Cmd-0.0.5-py3.6-nspkg.pth
etc/sms-cmd.service
etc/buoy/sms.yaml
sms/sms_cmd.py
test/__init__.py
test/commands_line_test.py
test/test_sms.py
SMS_Cmd-0.0.5.dist-info/METADATA
SMS_Cmd-0.0.5.dist-info/WHEEL
SMS_Cmd-0.0.5.dist-info/entry_points.txt
SMS_Cmd-0.0.5.dist-info/namespace_packages.txt
SMS_Cmd-0.0.5.dist-info/top_level.txt
SMS_Cmd-0.0.5.dist-info/RECORD
