Metadata-Version: 2.1
Name: SMS-Cmd
Version: 0.0.5
Summary: Service execute commands send by SMS
Home-page: https://gitlab.com/redmic-project/device/oag-buoy/sms
Author: Repositorio de Datos Marinos Integrados de Canarias
Author-email: info@redmic.es
License: MIT
Keywords: sms command
Platform: UNKNOWN
Classifier: Development Status :: 4 - Beta
Classifier: Intended Audience :: Developers
Classifier: Topic :: Software Development :: Build Tools
Classifier: License :: OSI Approved :: MIT License
Classifier: Programming Language :: Python :: 3.6
Requires-Dist: PyYAML
Requires-Dist: pypandoc
Requires-Dist: Buoy-Lib
Provides-Extra: dev
Requires-Dist: check-manifest ; extra == 'dev'
Provides-Extra: test
Requires-Dist: coverage ; extra == 'test'
